light_text_classification/__init__.py
light_text_classification-0.1.0.dist-info/AUTHORS.rst
light_text_classification-0.1.0.dist-info/LICENSE
light_text_classification-0.1.0.dist-info/METADATA
light_text_classification-0.1.0.dist-info/WHEEL
light_text_classification-0.1.0.dist-info/top_level.txt
light_text_classification-0.1.0.dist-info/RECORD
