Metadata-Version: 2.1
Name: light-text-classification
Version: 0.1.0
Summary: An example package. Generated with cookiecutter-pylibrary.
Home-page: https://github.com/classtag/light-text-classification
Author: Duo An
Author-email: anduo@qq.com
License: MIT license
Platform: UNKNOWN
Classifier: Development Status :: 5 - Production/Stable
Classifier: Intended Audience :: Developers
Classifier: License :: OSI Approved :: MIT License
Classifier: Operating System :: Unix
Classifier: Operating System :: POSIX
Classifier: Operating System :: Microsoft :: Windows
Classifier: Programming Language :: Python
Classifier: Programming Language :: Python :: 3.6
Classifier: Programming Language :: Python :: Implementation :: CPython
Classifier: Programming Language :: Python :: Implementation :: PyPy
Classifier: Topic :: Utilities
